aiocometd/__init__.py
aiocometd/_metadata.py
aiocometd/client.py
aiocometd/constants.py
aiocometd/exceptions.py
aiocometd/extensions.py
aiocometd/py.typed
aiocometd/typing.py
aiocometd/utils.py
aiocometd/transports/__init__.py
aiocometd/transports/abc.py
aiocometd/transports/base.py
aiocometd/transports/long_polling.py
aiocometd/transports/registry.py
aiocometd/transports/websocket.py
aiocometd-0.4.5.dist-info/LICENSE.txt
aiocometd-0.4.5.dist-info/METADATA
aiocometd-0.4.5.dist-info/WHEEL
aiocometd-0.4.5.dist-info/top_level.txt
aiocometd-0.4.5.dist-info/RECORD
