Metadata-Version: 2.1
Name: aiocometd
Version: 0.4.5
Summary: CometD client for asyncio
Home-page: https://github.com/robertmrk/aiocometd
Author: Róbert Márki
Author-email: gsmiko@gmail.com
License: MIT
Project-URL: CI, https://travis-ci.org/robertmrk/aiocometd
Project-URL: Coverage, https://coveralls.io/github/robertmrk/aiocometd
Project-URL: Docs, http://aiocometd.readthedocs.io/
Keywords: asyncio aiohttp comet cometd bayeux push streaming
Platform: UNKNOWN
Classifier: Programming Language :: Python
Classifier: Programming Language :: Python :: 3
Classifier: Programming Language :: Python :: 3.6
Classifier: Programming Language :: Python :: Implementation :: CPython
Classifier: Framework :: AsyncIO
Classifier: License :: OSI Approved :: MIT License
Requires-Python: >=3.6.0
Provides-Extra: examples
Provides-Extra: docs
Provides-Extra: tests
Provides-Extra: dev
